googlemaps/__init__.py
googlemaps/client.py
googlemaps/convert.py
googlemaps/directions.py
googlemaps/distance_matrix.py
googlemaps/elevation.py
googlemaps/exceptions.py
googlemaps/geocoding.py
googlemaps/geolocation.py
googlemaps/maps.py
googlemaps/places.py
googlemaps/roads.py
googlemaps/timezone.py
googlemaps-4.2.0.dist-info/AUTHORS
googlemaps-4.2.0.dist-info/LICENSE
googlemaps-4.2.0.dist-info/METADATA
googlemaps-4.2.0.dist-info/WHEEL
googlemaps-4.2.0.dist-info/top_level.txt
googlemaps-4.2.0.dist-info/RECORD
